<?xml version="1.0" encoding="UTF-8"?>
<!DOCTYPE SimpleWsdDoc SYSTEM "simple-wsd-doc.dtd">
<SimpleWsdDoc name="/written/email/lists-046-11489622.txt">
  <word text="/" break_level="NO_BREAK"/>
  <word text="written" break_level="NO_BREAK"/>
  <word text="/" break_level="NO_BREAK"/>
  <word text="email" break_level="NO_BREAK"/>
  <word text="/" break_level="NO_BREAK"/>
  <word text="lists" break_level="NO_BREAK"/>
  <word text="-" break_level="NO_BREAK"/>
  <word text="046" break_level="NO_BREAK"/>
  <word text="-" break_level="NO_BREAK"/>
  <word text="11489622.txt" break_level="NO_BREAK"/>
  <word text="docno" break_level="PARAGRAPH_BREAK"/>
  <word text="=" break_level="NO_BREAK"/>
  <word text="``" break_level="NO_BREAK"/>
  <word text="lists" break_level="NO_BREAK"/>
  <word text="-" break_level="NO_BREAK"/>
  <word text="046" break_level="NO_BREAK"/>
  <word text="-" break_level="NO_BREAK"/>
  <word text="11489622" break_level="NO_BREAK"/>
  <word text="&#39;&#39;" break_level="NO_BREAK"/>
  <word text="name" lemma="name" pos="NOUN" sense="/dictionary/sense/en_us_NOAD3e_2012/m_en_us1270390.001" break_level="LINE_BREAK"/>
  <word text="=" break_level="NO_BREAK"/>
  <word text="``" break_level="NO_BREAK"/>
  <word text="Dave" break_level="NO_BREAK"/>
  <word text="Raggett" break_level="SPACE_BREAK"/>
  <word text="&#39;&#39;" break_level="NO_BREAK"/>
  <word text="email" break_level="LINE_BREAK"/>
  <word text="=" break_level="NO_BREAK"/>
  <word text="``" break_level="NO_BREAK"/>
  <word text="dsr@w3.org" break_level="NO_BREAK"/>
  <word text="&#39;&#39;" break_level="NO_BREAK"/>
  <word text="sent" lemma="send" pos="VERB" sense="/dictionary/sense/en_us_NOAD3e_2012/m_en_us1289024.001" break_level="LINE_BREAK"/>
  <word text="=" break_level="NO_BREAK"/>
  <word text="``" break_level="NO_BREAK"/>
  <word text="Fri" break_level="NO_BREAK"/>
  <word text="," break_level="NO_BREAK"/>
  <word text="22" break_level="SPACE_BREAK"/>
  <word text="Mar" break_level="SPACE_BREAK"/>
  <word text="1996" break_level="SPACE_BREAK"/>
  <word text="18:19:06" break_level="SPACE_BREAK"/>
  <word text="-0500" break_level="SPACE_BREAK"/>
  <word text="&#39;&#39;" break_level="NO_BREAK"/>
  <word text="subject" lemma="subject" pos="NOUN" sense="/dictionary/sense/en_us_NOAD3e_2012/m_en_us1295267.001" break_level="LINE_BREAK"/>
  <word text="=" break_level="NO_BREAK"/>
  <word text="``" break_level="NO_BREAK"/>
  <word text="Minutes" lemma="minute" pos="NOUN" sense="/dictionary/sense/en_us_NOAD3e_2012/m_en_us1268240.001" break_level="NO_BREAK"/>
  <word text="for" break_level="SPACE_BREAK"/>
  <word text="18th" break_level="SPACE_BREAK"/>
  <word text="March" break_level="SPACE_BREAK"/>
  <word text="&#39;&#39;" break_level="NO_BREAK"/>
  <word text="To" break_level="LINE_BREAK"/>
  <word text=":" break_level="NO_BREAK"/>
  <word text="w3c" break_level="SPACE_BREAK"/>
  <word text="-" break_level="NO_BREAK"/>
  <word text="math" break_level="NO_BREAK"/>
  <word text="-" break_level="NO_BREAK"/>
  <word text="erb@w3.org" break_level="NO_BREAK"/>
  <word text="Meeting" lemma="meeting" pos="NOUN" sense="/dictionary/sense/en_us_NOAD3e_2012/m_en_us1266936.003" break_level="PARAGRAPH_BREAK"/>
  <word text="Notes" break_level="SPACE_BREAK"/>
  <word text="of" break_level="SPACE_BREAK"/>
  <word text="Math" break_level="SPACE_BREAK"/>
  <word text="-" break_level="NO_BREAK"/>
  <word text="ERB" break_level="NO_BREAK"/>
  <word text="Teleconference" break_level="SPACE_BREAK"/>
  <word text=":" break_level="NO_BREAK"/>
  <word text="Thursday" break_level="SENTENCE_BREAK"/>
  <word text="18th" break_level="SPACE_BREAK"/>
  <word text="March" break_level="SPACE_BREAK"/>
  <word text="&#39;" break_level="SPACE_BREAK"/>
  <word text="96" break_level="NO_BREAK"/>
  <word text="Present" break_level="PARAGRAPH_BREAK"/>
  <word text=":" break_level="NO_BREAK"/>
  <word text="Bruce" break_level="PARAGRAPH_BREAK"/>
  <word text="Smith" break_level="SPACE_BREAK"/>
  <word text="," break_level="NO_BREAK"/>
  <word text="Wolfram" break_level="SPACE_BREAK"/>
  <word text="Neil" break_level="LINE_BREAK"/>
  <word text="Soiffer" break_level="SPACE_BREAK"/>
  <word text="," break_level="NO_BREAK"/>
  <word text="Wolfram" break_level="SPACE_BREAK"/>
  <word text="T.V." break_level="LINE_BREAK"/>
  <word text="Raman" break_level="SPACE_BREAK"/>
  <word text="," break_level="NO_BREAK"/>
  <word text="Adobe" break_level="SPACE_BREAK"/>
  <word text="Dave" break_level="LINE_BREAK"/>
  <word text="Raggett" break_level="SPACE_BREAK"/>
  <word text="," break_level="NO_BREAK"/>
  <word text="W3C" break_level="SPACE_BREAK"/>
  <word text="Meeting" lemma="meeting" pos="NOUN" sense="/dictionary/sense/en_us_NOAD3e_2012/m_en_us1266936.003" break_level="PARAGRAPH_BREAK"/>
  <word text="time" break_level="SPACE_BREAK"/>
  <word text="/" break_level="NO_BREAK"/>
  <word text="frequency" lemma="frequency" pos="NOUN" sense="/dictionary/sense/en_us_NOAD3e_2012/m_en_us1249056.001" break_level="NO_BREAK"/>
  <word text="Dave" break_level="PARAGRAPH_BREAK"/>
  <word text="has" lemma="have" pos="VERB" sense="/dictionary/sense/en_us_NOAD3e_2012/m_en_us1253820.034" break_level="SPACE_BREAK"/>
  <word text="been" break_level="SPACE_BREAK"/>
  <word text="unable" break_level="SPACE_BREAK"/>
  <word text="to" break_level="SPACE_BREAK"/>
  <word text="find" lemma="find" pos="VERB" sense="/dictionary/sense/en_us_NOAD3e_2012/m_en_us1247107.008" break_level="SPACE_BREAK"/>
  <word text="any" break_level="SPACE_BREAK"/>
  <word text="time" break_level="SPACE_BREAK"/>
  <word text="that" break_level="SPACE_BREAK"/>
  <word text="all" break_level="SPACE_BREAK"/>
  <word text="of" break_level="SPACE_BREAK"/>
  <word text="us" break_level="SPACE_BREAK"/>
  <word text="can" lemma="can" pos="VERB" sense="/dictionary/sense/en_us_NOAD3e_2012/m_en_us1230339.001" break_level="SPACE_BREAK"/>
  <word text="make" break_level="SPACE_BREAK"/>
  <word text="." break_level="NO_BREAK"/>
  <word text="The" break_level="SENTENCE_BREAK"/>
  <word text="new" break_level="SPACE_BREAK"/>
  <word text="time" break_level="SPACE_BREAK"/>
  <word text="will" break_level="LINE_BREAK"/>
  <word text="be" break_level="SPACE_BREAK"/>
  <word text="every" break_level="SPACE_BREAK"/>
  <word text="Monday" break_level="SPACE_BREAK"/>
  <word text="at" break_level="SPACE_BREAK"/>
  <word text="1300" break_level="SPACE_BREAK"/>
  <word text="EST" break_level="SPACE_BREAK"/>
  <word text="until" break_level="SPACE_BREAK"/>
  <word text="further" lemma="further" pos="ADJ" sense="/dictionary/sense/en_us_NOAD3e_2012/m_en_us1249623.011" break_level="SPACE_BREAK"/>
  <word text="notice" lemma="notice" pos="NOUN" sense="/dictionary/sense/en_us_NOAD3e_2012/m_en_us1272186.002" break_level="SPACE_BREAK"/>
  <word text="." break_level="NO_BREAK"/>
  <word text="Dave" break_level="SENTENCE_BREAK"/>
  <word text="will" break_level="SPACE_BREAK"/>
  <word text="attempt" break_level="SPACE_BREAK"/>
  <word text="to" break_level="SPACE_BREAK"/>
  <word text="keep" lemma="keep" pos="VERB" sense="/dictionary/sense/en_us_NOAD3e_2012/m_en_us1260682.006" break_level="LINE_BREAK"/>
  <word text="Nico" break_level="SPACE_BREAK"/>
  <word text="in" break_level="SPACE_BREAK"/>
  <word text="the" break_level="SPACE_BREAK"/>
  <word text="loop" lemma="loop" pos="NOUN" sense="/dictionary/sense/en_us_NOAD3e_2012/m_en_us1264324.007" break_level="SPACE_BREAK"/>
  <word text="via" break_level="SPACE_BREAK"/>
  <word text="email" break_level="SPACE_BREAK"/>
  <word text="on" break_level="SPACE_BREAK"/>
  <word text="the" break_level="SPACE_BREAK"/>
  <word text="mailing" lemma="mailing" pos="NOUN" sense="/dictionary/sense/en_us_NOAD3e_2012/m_en_us1265401.001" break_level="SPACE_BREAK"/>
  <word text="list" lemma="list" pos="NOUN" sense="/dictionary/sense/en_us_NOAD3e_2012/m_en_us1263771.001" break_level="SPACE_BREAK"/>
  <word text="and" break_level="SPACE_BREAK"/>
  <word text="separate" break_level="SPACE_BREAK"/>
  <word text="phone" lemma="phone" pos="NOUN" sense="/dictionary/sense/en_us_NOAD3e_2012/m_en_us1277599.001" break_level="SPACE_BREAK"/>
  <word text="calls" lemma="call" pos="NOUN" sense="/dictionary/sense/en_us_NOAD3e_2012/m_en_us1230162.019" break_level="SPACE_BREAK"/>
  <word text="." break_level="NO_BREAK"/>
  <word text="Adding" lemma="add" pos="VERB" sense="/dictionary/sense/en_us_NOAD3e_2012/m_en_us1219879.001" break_level="PARAGRAPH_BREAK"/>
  <word text="further" lemma="further" pos="ADJ" sense="/dictionary/sense/en_us_NOAD3e_2012/m_en_us1249623.011" break_level="SPACE_BREAK"/>
  <word text="People" lemma="people" pos="NOUN" sense="/dictionary/sense/en_us_NOAD3e_2012/m_en_us1276782.001" break_level="SPACE_BREAK"/>
  <word text="to" break_level="SPACE_BREAK"/>
  <word text="the" break_level="SPACE_BREAK"/>
  <word text="Math" break_level="SPACE_BREAK"/>
  <word text="-" break_level="NO_BREAK"/>
  <word text="ERB" break_level="NO_BREAK"/>
  <word text="Stu" break_level="PARAGRAPH_BREAK"/>
  <word text="Weibel" break_level="SPACE_BREAK"/>
  <word text="of" break_level="SPACE_BREAK"/>
  <word text="OCLC" break_level="SPACE_BREAK"/>
  <word text="sends" lemma="send" pos="VERB" sense="/dictionary/sense/en_us_NOAD3e_2012/m_en_us1289024.001" break_level="SPACE_BREAK"/>
  <word text="his" break_level="SPACE_BREAK"/>
  <word text="regrets" break_level="SPACE_BREAK"/>
  <word text="that" break_level="SPACE_BREAK"/>
  <word text="they" break_level="SPACE_BREAK"/>
  <word text="are" lemma="be" pos="VERB" sense="/dictionary/sense/en_us_NOAD3e_2012/m_en_us1225404.008" break_level="SPACE_BREAK"/>
  <word text="too" lemma="too" pos="ADV" sense="/dictionary/sense/en_us_NOAD3e_2012/m_en_us1299350.001" break_level="SPACE_BREAK"/>
  <word text="busy" break_level="SPACE_BREAK"/>
  <word text="to" break_level="SPACE_BREAK"/>
  <word text="accept" lemma="accept" pos="VERB" sense="/dictionary/sense/en_us_NOAD3e_2012/m_en_us1219519.001" break_level="SPACE_BREAK"/>
  <word text="the" break_level="SPACE_BREAK"/>
  <word text="invitation" break_level="LINE_BREAK"/>
  <word text="at" break_level="SPACE_BREAK"/>
  <word text="this" break_level="SPACE_BREAK"/>
  <word text="time" break_level="SPACE_BREAK"/>
  <word text="." break_level="NO_BREAK"/>
  <word text="Elsevier" break_level="SENTENCE_BREAK"/>
  <word text="have" lemma="have" pos="VERB" sense="/dictionary/sense/en_us_NOAD3e_2012/m_en_us1253820.034" break_level="SPACE_BREAK"/>
  <word text="contacted" break_level="SPACE_BREAK"/>
  <word text="the" break_level="SPACE_BREAK"/>
  <word text="AMS" break_level="SPACE_BREAK"/>
  <word text="." break_level="NO_BREAK"/>
  <word text="Ralph" break_level="SENTENCE_BREAK"/>
  <word text="Youngen" break_level="SPACE_BREAK"/>
  <word text="," break_level="NO_BREAK"/>
  <word text="Associate" break_level="LINE_BREAK"/>
  <word text="Director" break_level="SPACE_BREAK"/>
  <word text="," break_level="NO_BREAK"/>
  <word text="Electronic" break_level="SPACE_BREAK"/>
  <word text="Product" lemma="product" pos="NOUN" sense="/dictionary/sense/en_us_NOAD3e_2012/m_en_us1280957.001" break_level="SPACE_BREAK"/>
  <word text="Development" lemma="development" pos="NOUN" sense="/dictionary/sense/en_us_NOAD3e_2012/m_en_us1239901.001" break_level="SPACE_BREAK"/>
  <word text="for" break_level="SPACE_BREAK"/>
  <word text="AMS" break_level="SPACE_BREAK"/>
  <word text="has" lemma="have" pos="VERB" sense="/dictionary/sense/en_us_NOAD3e_2012/m_en_us1253820.034" break_level="SPACE_BREAK"/>
  <word text="accepted" lemma="accept" pos="VERB" sense="/dictionary/sense/en_us_NOAD3e_2012/m_en_us1219519.001" break_level="SPACE_BREAK"/>
  <word text="the" break_level="SPACE_BREAK"/>
  <word text="invitation" break_level="LINE_BREAK"/>
  <word text="to" break_level="SPACE_BREAK"/>
  <word text="join" break_level="SPACE_BREAK"/>
  <word text="the" break_level="SPACE_BREAK"/>
  <word text="group" break_level="SPACE_BREAK"/>
  <word text="," break_level="NO_BREAK"/>
  <word text="along" break_level="SPACE_BREAK"/>
  <word text="with" break_level="SPACE_BREAK"/>
  <word text="a" break_level="SPACE_BREAK"/>
  <word text="couple" lemma="couple" pos="NOUN" sense="/dictionary/sense/en_us_NOAD3e_2012/m_en_us1236569.001" break_level="SPACE_BREAK"/>
  <word text="of" break_level="SPACE_BREAK"/>
  <word text="his" break_level="SPACE_BREAK"/>
  <word text="colleagues" break_level="SPACE_BREAK"/>
  <word text="." break_level="NO_BREAK"/>
  <word text="The" break_level="PARAGRAPH_BREAK"/>
  <word text="need" lemma="need" pos="NOUN" sense="/dictionary/sense/en_us_NOAD3e_2012/m_en_us1270832.005" break_level="SPACE_BREAK"/>
  <word text="for" break_level="SPACE_BREAK"/>
  <word text="full" lemma="full" pos="ADJ" sense="/dictionary/sense/en_us_NOAD3e_2012/m_en_us1249427.008" break_level="SPACE_BREAK"/>
  <word text="SGML" break_level="SPACE_BREAK"/>
  <word text="?" break_level="NO_BREAK"/>
  <word text="We" break_level="PARAGRAPH_BREAK"/>
  <word text="discussed" break_level="SPACE_BREAK"/>
  <word text="whether" break_level="SPACE_BREAK"/>
  <word text="it" break_level="SPACE_BREAK"/>
  <word text="was" break_level="SPACE_BREAK"/>
  <word text="necessary" lemma="necessary" pos="ADJ" sense="/dictionary/sense/en_us_NOAD3e_2012/m_en_us1270794.001" break_level="SPACE_BREAK"/>
  <word text="to" break_level="SPACE_BREAK"/>
  <word text="use" lemma="use" pos="VERB" sense="/dictionary/sense/en_us_NOAD3e_2012/m_en_us1303226.001" break_level="SPACE_BREAK"/>
  <word text="SGML" break_level="SPACE_BREAK"/>
  <word text="for" break_level="SPACE_BREAK"/>
  <word text="the" break_level="SPACE_BREAK"/>
  <word text="math" break_level="SPACE_BREAK"/>
  <word text="notation" lemma="notation" pos="NOUN" sense="/dictionary/sense/en_us_NOAD3e_2012/m_en_us1272166.001" break_level="SPACE_BREAK"/>
  <word text="." break_level="NO_BREAK"/>
  <word text="Basically" break_level="SENTENCE_BREAK"/>
  <word text="," break_level="NO_BREAK"/>
  <word text="we" break_level="SPACE_BREAK"/>
  <word text="have" lemma="have" pos="VERB" sense="/dictionary/sense/en_us_NOAD3e_2012/m_en_us1253820.001" break_level="SPACE_BREAK"/>
  <word text="a" break_level="SPACE_BREAK"/>
  <word text="preference" lemma="preference" pos="NOUN" sense="/dictionary/sense/en_us_NOAD3e_2012/m_en_us1280303.001" break_level="SPACE_BREAK"/>
  <word text="for" break_level="SPACE_BREAK"/>
  <word text="an" break_level="SPACE_BREAK"/>
  <word text="extensible" break_level="SPACE_BREAK"/>
  <word text="operator" lemma="operator" pos="NOUN" sense="/dictionary/sense/en_us_NOAD3e_2012/m_en_us1273617.005" break_level="SPACE_BREAK"/>
  <word text="precedence" break_level="SPACE_BREAK"/>
  <word text="notation" break_level="LINE_BREAK"/>
  <word text="." break_level="NO_BREAK"/>
  <word text="This" break_level="SENTENCE_BREAK"/>
  <word text="can" lemma="can" pos="VERB" sense="/dictionary/sense/en_us_NOAD3e_2012/m_en_us1230339.001" break_level="SPACE_BREAK"/>
  <word text="be" break_level="SPACE_BREAK"/>
  <word text="included" lemma="include" pos="VERB" sense="/dictionary/sense/en_us_NOAD3e_2012/m_en_us1257529.002" break_level="SPACE_BREAK"/>
  <word text="in" break_level="SPACE_BREAK"/>
  <word text="HTML" break_level="SPACE_BREAK"/>
  <word text="documents" break_level="SPACE_BREAK"/>
  <word text="and" break_level="SPACE_BREAK"/>
  <word text="handled" lemma="handle" pos="VERB" sense="/dictionary/sense/en_us_NOAD3e_2012/m_en_us1253407.004" break_level="SPACE_BREAK"/>
  <word text="correctly" break_level="SPACE_BREAK"/>
  <word text="by" break_level="SPACE_BREAK"/>
  <word text="SGML" break_level="LINE_BREAK"/>
  <word text="processing" lemma="process" pos="NOUN" sense="/dictionary/sense/en_us_NOAD3e_2012/m_en_us1280909.001" break_level="SPACE_BREAK"/>
  <word text="applications" lemma="application" pos="NOUN" sense="/dictionary/sense/en_us_NOAD3e_2012/m_en_us1222524.008" break_level="SPACE_BREAK"/>
  <word text="via" break_level="SPACE_BREAK"/>
  <word text="the" break_level="SPACE_BREAK"/>
  <word text="NOTATION" break_level="SPACE_BREAK"/>
  <word text="mechanism" lemma="mechanism" pos="NOUN" sense="/dictionary/sense/en_us_NOAD3e_2012/m_en_us1266821.002" break_level="SPACE_BREAK"/>
  <word text="." break_level="NO_BREAK"/>
  <word text="When" break_level="PARAGRAPH_BREAK"/>
  <word text="using" lemma="use" pos="VERB" sense="/dictionary/sense/en_us_NOAD3e_2012/m_en_us1303226.001" break_level="SPACE_BREAK"/>
  <word text="operator" lemma="operator" pos="NOUN" sense="/dictionary/sense/en_us_NOAD3e_2012/m_en_us1273617.005" break_level="SPACE_BREAK"/>
  <word text="precedence" break_level="SPACE_BREAK"/>
  <word text="," break_level="NO_BREAK"/>
  <word text="there" break_level="SPACE_BREAK"/>
  <word text="is" lemma="be" pos="VERB" sense="/dictionary/sense/en_us_NOAD3e_2012/m_en_us1225404.008" break_level="SPACE_BREAK"/>
  <word text="a" break_level="SPACE_BREAK"/>
  <word text="need" lemma="need" pos="NOUN" sense="/dictionary/sense/en_us_NOAD3e_2012/m_en_us1270832.005" break_level="SPACE_BREAK"/>
  <word text="to" break_level="SPACE_BREAK"/>
  <word text="constrain" break_level="SPACE_BREAK"/>
  <word text="the" break_level="SPACE_BREAK"/>
  <word text="context" break_level="SPACE_BREAK"/>
  <word text="in" break_level="SPACE_BREAK"/>
  <word text="which" break_level="LINE_BREAK"/>
  <word text="given" break_level="SPACE_BREAK"/>
  <word text="operators" lemma="operator" pos="NOUN" sense="/dictionary/sense/en_us_NOAD3e_2012/m_en_us1273617.005" break_level="SPACE_BREAK"/>
  <word text="can" lemma="can" pos="VERB" sense="/dictionary/sense/en_us_NOAD3e_2012/m_en_us1230339.001" break_level="SPACE_BREAK"/>
  <word text="be" break_level="SPACE_BREAK"/>
  <word text="used" lemma="use" pos="VERB" sense="/dictionary/sense/en_us_NOAD3e_2012/m_en_us1303226.001" break_level="SPACE_BREAK"/>
  <word text="." break_level="NO_BREAK"/>
  <word text="Niel" break_level="SENTENCE_BREAK"/>
  <word text="said" lemma="say" pos="VERB" sense="/dictionary/sense/en_us_NOAD3e_2012/m_en_us1287486.001" break_level="SPACE_BREAK"/>
  <word text="this" break_level="SPACE_BREAK"/>
  <word text="was" break_level="SPACE_BREAK"/>
  <word text="n&#39;t" break_level="NO_BREAK"/>
  <word text="as" break_level="SPACE_BREAK"/>
  <word text="simple" break_level="SPACE_BREAK"/>
  <word text="as" break_level="SPACE_BREAK"/>
  <word text="at" break_level="SPACE_BREAK"/>
  <word text="first" break_level="LINE_BREAK"/>
  <word text="it" break_level="SPACE_BREAK"/>
  <word text="might" lemma="might" pos="VERB" sense="/dictionary/sense/en_us_NOAD3e_2012/m_en_us1267902.010" break_level="SPACE_BREAK"/>
  <word text="appear" lemma="appear" pos="VERB" sense="/dictionary/sense/en_us_NOAD3e_2012/m_en_us1222474.008" break_level="SPACE_BREAK"/>
  <word text="." break_level="NO_BREAK"/>
  <word text="Dave" break_level="SENTENCE_BREAK"/>
  <word text="will" break_level="SPACE_BREAK"/>
  <word text="work" lemma="work" pos="VERB" sense="/dictionary/sense/en_us_NOAD3e_2012/m_en_us1307050.020" break_level="SPACE_BREAK"/>
  <word text="on" break_level="SPACE_BREAK"/>
  <word text="a" break_level="SPACE_BREAK"/>
  <word text="formal" lemma="formal" pos="ADJ" sense="/dictionary/sense/en_us_NOAD3e_2012/m_en_us1248517.005" break_level="SPACE_BREAK"/>
  <word text="mechanism" lemma="mechanism" pos="NOUN" sense="/dictionary/sense/en_us_NOAD3e_2012/m_en_us1266821.002" break_level="SPACE_BREAK"/>
  <word text="for" break_level="SPACE_BREAK"/>
  <word text="this" break_level="SPACE_BREAK"/>
  <word text="." break_level="NO_BREAK"/>
  <word text="It" break_level="PARAGRAPH_BREAK"/>
  <word text="is" lemma="be" pos="VERB" sense="/dictionary/sense/en_us_NOAD3e_2012/m_en_us1225404.008" break_level="SPACE_BREAK"/>
  <word text="also" break_level="SPACE_BREAK"/>
  <word text="unclear" break_level="SPACE_BREAK"/>
  <word text="as" break_level="SPACE_BREAK"/>
  <word text="to" break_level="SPACE_BREAK"/>
  <word text="when" lemma="when" pos="ADV" sense="/dictionary/sense/en_us_NOAD3e_2012/m_en_us1305963.004" break_level="SPACE_BREAK"/>
  <word text="macro" lemma="macro" pos="ADJ" sense="/dictionary/sense/en_us_NOAD3e_2012/m_en_us1265132.003" break_level="SPACE_BREAK"/>
  <word text="processing" lemma="process" pos="NOUN" sense="/dictionary/sense/en_us_NOAD3e_2012/m_en_us1280909.001" break_level="SPACE_BREAK"/>
  <word text="is" break_level="SPACE_BREAK"/>
  <word text="applied" lemma="apply" pos="VERB" sense="/dictionary/sense/en_us_NOAD3e_2012/m_en_us1222532.007" break_level="SPACE_BREAK"/>
  <word text="." break_level="NO_BREAK"/>
  <word text="Further" lemma="further" pos="ADJ" sense="/dictionary/sense/en_us_NOAD3e_2012/m_en_us1249623.011" break_level="SENTENCE_BREAK"/>
  <word text="discussion" break_level="SPACE_BREAK"/>
  <word text="on" break_level="LINE_BREAK"/>
  <word text="this" break_level="SPACE_BREAK"/>
  <word text="is" break_level="SPACE_BREAK"/>
  <word text="needed" break_level="SPACE_BREAK"/>
  <word text="." break_level="NO_BREAK"/>
  <word text="It" break_level="SENTENCE_BREAK"/>
  <word text="should" lemma="should" pos="VERB" sense="/dictionary/sense/en_us_NOAD3e_2012/m_en_us1290273.001" break_level="SPACE_BREAK"/>
  <word text="be" break_level="SPACE_BREAK"/>
  <word text="practical" lemma="practical" pos="ADJ" sense="/dictionary/sense/en_us_NOAD3e_2012/m_en_us1280071.001" break_level="SPACE_BREAK"/>
  <word text="for" break_level="SPACE_BREAK"/>
  <word text="parsers" break_level="SPACE_BREAK"/>
  <word text="to" break_level="SPACE_BREAK"/>
  <word text="deal" lemma="deal" pos="VERB" sense="/dictionary/sense/en_us_NOAD3e_2012/m_en_us1238634.007" break_level="SPACE_BREAK"/>
  <word text="with" break_level="SPACE_BREAK"/>
  <word text="missing" lemma="missing" pos="ADJ" sense="/dictionary/sense/en_us_NOAD3e_2012/m_en_us1268421.001" break_level="SPACE_BREAK"/>
  <word text="arguments" lemma="argument" pos="NOUN" sense="/dictionary/sense/en_us_NOAD3e_2012/m_en_us1222866.002" break_level="LINE_BREAK"/>
  <word text="sensibly" break_level="SPACE_BREAK"/>
  <word text="." break_level="NO_BREAK"/>
  <word text="This" break_level="SENTENCE_BREAK"/>
  <word text="in" break_level="SPACE_BREAK"/>
  <word text="general" lemma="general" pos="ADJ" sense="/dictionary/sense/en_us_NOAD3e_2012/m_en_us1250413.001" break_level="SPACE_BREAK"/>
  <word text="depends" lemma="depend" pos="VERB" sense="/dictionary/sense/en_us_NOAD3e_2012/m_en_us1239513.001" break_level="SPACE_BREAK"/>
  <word text="on" break_level="SPACE_BREAK"/>
  <word text="the" break_level="SPACE_BREAK"/>
  <word text="context" break_level="SPACE_BREAK"/>
  <word text="." break_level="NO_BREAK"/>
  <word text="Raman" break_level="PARAGRAPH_BREAK"/>
  <word text="voiced" lemma="voice" pos="VERB" sense="/dictionary/sense/en_us_NOAD3e_2012/m_en_us1304594.015" break_level="SPACE_BREAK"/>
  <word text="a" break_level="SPACE_BREAK"/>
  <word text="concern" lemma="concern" pos="NOUN" sense="/dictionary/sense/en_us_NOAD3e_2012/m_en_us1235108.007" break_level="SPACE_BREAK"/>
  <word text="on" break_level="SPACE_BREAK"/>
  <word text="Bruce" break_level="SPACE_BREAK"/>
  <word text="&#39;s" break_level="NO_BREAK"/>
  <word text="comment" break_level="SPACE_BREAK"/>
  <word text="on" break_level="SPACE_BREAK"/>
  <word text="2D" break_level="SPACE_BREAK"/>
  <word text="pictures" break_level="SPACE_BREAK"/>
  <word text="." break_level="NO_BREAK"/>
  <word text="We" break_level="SENTENCE_BREAK"/>
  <word text="agreed" lemma="agree" pos="VERB" sense="/dictionary/sense/en_us_NOAD3e_2012/m_en_us1220472.001" break_level="SPACE_BREAK"/>
  <word text="however" lemma="however" pos="ADV" sense="/dictionary/sense/en_us_NOAD3e_2012/m_en_us1256065.001" break_level="SPACE_BREAK"/>
  <word text="," break_level="NO_BREAK"/>
  <word text="that" break_level="LINE_BREAK"/>
  <word text="a" break_level="SPACE_BREAK"/>
  <word text="fixed" lemma="fixed" pos="ADJ" sense="/dictionary/sense/en_us_NOAD3e_2012/m_en_us1247444.001" break_level="SPACE_BREAK"/>
  <word text="set" lemma="set" pos="NOUN" sense="/dictionary/sense/en_us_NOAD3e_2012/m_en_us1289371.001" break_level="SPACE_BREAK"/>
  <word text="of" break_level="SPACE_BREAK"/>
  <word text="``" break_level="SPACE_BREAK"/>
  <word text="layout" break_level="NO_BREAK"/>
  <word text="&#39;&#39;" break_level="NO_BREAK"/>
  <word text="idioms" break_level="SPACE_BREAK"/>
  <word text="are" lemma="be" pos="VERB" sense="/dictionary/sense/en_us_NOAD3e_2012/m_en_us1225404.008" break_level="SPACE_BREAK"/>
  <word text="sufficient" break_level="SPACE_BREAK"/>
  <word text="for" break_level="SPACE_BREAK"/>
  <word text="HTML" break_level="SPACE_BREAK"/>
  <word text="-" break_level="NO_BREAK"/>
  <word text="math." break_level="NO_BREAK"/>
  <word text="Raman" break_level="SPACE_BREAK"/>
  <word text="promised" lemma="promise" pos="VERB" sense="/dictionary/sense/en_us_NOAD3e_2012/m_en_us1281085.004" break_level="LINE_BREAK"/>
  <word text="to" break_level="SPACE_BREAK"/>
  <word text="propose" lemma="propose" pos="VERB" sense="/dictionary/sense/en_us_NOAD3e_2012/m_en_us1281190.001" break_level="SPACE_BREAK"/>
  <word text="some" break_level="SPACE_BREAK"/>
  <word text="new" break_level="SPACE_BREAK"/>
  <word text="wording" break_level="SPACE_BREAK"/>
  <word text="." break_level="NO_BREAK"/>
  <word text="He" break_level="SENTENCE_BREAK"/>
  <word text="also" break_level="SPACE_BREAK"/>
  <word text="gave" lemma="give" pos="VERB" sense="/dictionary/sense/en_us_NOAD3e_2012/m_en_us1250951.015" break_level="SPACE_BREAK"/>
  <word text="us" break_level="SPACE_BREAK"/>
  <word text="a" break_level="SPACE_BREAK"/>
  <word text="URL" break_level="SPACE_BREAK"/>
  <word text="for" break_level="SPACE_BREAK"/>
  <word text="his" break_level="SPACE_BREAK"/>
  <word text="test" lemma="test" pos="NOUN" sense="/dictionary/sense/en_us_NOAD3e_2012/m_en_us1297943.001" break_level="SPACE_BREAK"/>
  <word text="suite" lemma="suite" pos="NOUN" sense="/dictionary/sense/en_us_NOAD3e_2012/m_en_us1295570.001" break_level="LINE_BREAK"/>
  <word text="," break_level="NO_BREAK"/>
  <word text="which" break_level="SPACE_BREAK"/>
  <word text="I" break_level="SPACE_BREAK"/>
  <word text="have" lemma="have" pos="VERB" sense="/dictionary/sense/en_us_NOAD3e_2012/m_en_us1253820.034" break_level="SPACE_BREAK"/>
  <word text="added" lemma="add" pos="VERB" sense="/dictionary/sense/en_us_NOAD3e_2012/m_en_us1219879.001" break_level="SPACE_BREAK"/>
  <word text="to" break_level="SPACE_BREAK"/>
  <word text="the" break_level="SPACE_BREAK"/>
  <word text="math" break_level="SPACE_BREAK"/>
  <word text="-" break_level="NO_BREAK"/>
  <word text="erb" break_level="NO_BREAK"/>
  <word text="home" break_level="SPACE_BREAK"/>
  <word text="page" lemma="page" pos="NOUN" sense="/dictionary/sense/en_us_NOAD3e_2012/m_en_us1274966.001" break_level="SPACE_BREAK"/>
  <word text="." break_level="NO_BREAK"/>
  <word text="We" break_level="PARAGRAPH_BREAK"/>
  <word text="ended" break_level="SPACE_BREAK"/>
  <word text="by" break_level="SPACE_BREAK"/>
  <word text="discussing" break_level="SPACE_BREAK"/>
  <word text="some" break_level="SPACE_BREAK"/>
  <word text="of" break_level="SPACE_BREAK"/>
  <word text="the" break_level="SPACE_BREAK"/>
  <word text="parsing" break_level="SPACE_BREAK"/>
  <word text="issues" lemma="issue" pos="NOUN" sense="/dictionary/sense/en_us_NOAD3e_2012/m_en_us1259315.001" break_level="SPACE_BREAK"/>
  <word text="for" break_level="SPACE_BREAK"/>
  <word text="mismatched" break_level="SPACE_BREAK"/>
  <word text="brackets" lemma="bracket" pos="NOUN" sense="/dictionary/sense/en_us_NOAD3e_2012/m_en_us1228359.001" break_level="SPACE_BREAK"/>
  <word text="and" break_level="SPACE_BREAK"/>
  <word text="number" lemma="number" pos="NOUN" sense="/dictionary/sense/en_us_NOAD3e_2012/m_en_us1272399.001" break_level="LINE_BREAK"/>
  <word text="literals" break_level="SPACE_BREAK"/>
  <word text="." break_level="NO_BREAK"/>
  <word text="It" break_level="SENTENCE_BREAK"/>
  <word text="seems" break_level="SPACE_BREAK"/>
  <word text="clear" lemma="clear" pos="ADJ" sense="/dictionary/sense/en_us_NOAD3e_2012/m_en_us1233608.001" break_level="SPACE_BREAK"/>
  <word text="that" break_level="SPACE_BREAK"/>
  <word text="bracket" lemma="bracket" pos="NOUN" sense="/dictionary/sense/en_us_NOAD3e_2012/m_en_us1228359.001" break_level="SPACE_BREAK"/>
  <word text="matching" break_level="SPACE_BREAK"/>
  <word text="ca" break_level="SPACE_BREAK"/>
  <word text="n&#39;t" break_level="NO_BREAK"/>
  <word text="in" break_level="SPACE_BREAK"/>
  <word text="general" lemma="general" pos="ADJ" sense="/dictionary/sense/en_us_NOAD3e_2012/m_en_us1250413.005" break_level="SPACE_BREAK"/>
  <word text="be" break_level="SPACE_BREAK"/>
  <word text="required" break_level="LINE_BREAK"/>
  <word text="." break_level="NO_BREAK"/>
  <word text="Authors" break_level="SENTENCE_BREAK"/>
  <word text="should" lemma="should" pos="VERB" sense="/dictionary/sense/en_us_NOAD3e_2012/m_en_us1290273.001" break_level="SPACE_BREAK"/>
  <word text="be" break_level="SPACE_BREAK"/>
  <word text="able" lemma="able" pos="ADJ" sense="/dictionary/sense/en_us_NOAD3e_2012/m_en_us1219312.001" break_level="SPACE_BREAK"/>
  <word text="to" break_level="SPACE_BREAK"/>
  <word text="control" lemma="control" pos="VERB" sense="/dictionary/sense/en_us_NOAD3e_2012/m_en_us1235733.013" break_level="SPACE_BREAK"/>
  <word text="the" break_level="SPACE_BREAK"/>
  <word text="settings" break_level="SPACE_BREAK"/>
  <word text="for" break_level="SPACE_BREAK"/>
  <word text="this" break_level="SPACE_BREAK"/>
  <word text="and" break_level="SPACE_BREAK"/>
  <word text="for" break_level="SPACE_BREAK"/>
  <word text="literals" break_level="LINE_BREAK"/>
  <word text="." break_level="NO_BREAK"/>
  <word text="Dave" break_level="PARAGRAPH_BREAK"/>
  <word text="has" lemma="have" pos="VERB" sense="/dictionary/sense/en_us_NOAD3e_2012/m_en_us1253820.034" break_level="SPACE_BREAK"/>
  <word text="posted" lemma="post" pos="VERB" sense="/dictionary/sense/en_us_NOAD3e_2012/m_en_us1279744.004" break_level="SPACE_BREAK"/>
  <word text="a" break_level="SPACE_BREAK"/>
  <word text="dump" lemma="dump" pos="NOUN" sense="/dictionary/sense/en_us_NOAD3e_2012/m_en_us1242471.001" break_level="SPACE_BREAK"/>
  <word text="of" break_level="SPACE_BREAK"/>
  <word text="his" break_level="SPACE_BREAK"/>
  <word text="understanding" break_level="SPACE_BREAK"/>
  <word text="as" break_level="SPACE_BREAK"/>
  <word text="a" break_level="SPACE_BREAK"/>
  <word text="result" break_level="SPACE_BREAK"/>
  <word text="of" break_level="SPACE_BREAK"/>
  <word text="this" break_level="SPACE_BREAK"/>
  <word text="conference" lemma="conference" pos="NOUN" sense="/dictionary/sense/en_us_NOAD3e_2012/m_en_us1235250.001" break_level="SPACE_BREAK"/>
  <word text="call" lemma="call" pos="NOUN" sense="/dictionary/sense/en_us_NOAD3e_2012/m_en_us1230162.019" break_level="LINE_BREAK"/>
  <word text="." break_level="NO_BREAK"/>
  <word text="See" lemma="see" pos="VERB" sense="/dictionary/sense/en_us_NOAD3e_2012/m_en_us1428150.001" break_level="SENTENCE_BREAK"/>
  <word text=":" break_level="NO_BREAK"/>
  <word text="current" break_level="SPACE_BREAK"/>
  <word text="thoughts" lemma="thought" pos="NOUN" sense="/dictionary/sense/en_us_NOAD3e_2012/m_en_us1298483.001" break_level="SPACE_BREAK"/>
  <word text="." break_level="NO_BREAK"/>
  <word text="Dave" break_level="PARAGRAPH_BREAK"/>
  <word text="Raggett" break_level="SPACE_BREAK"/>
  <word text="," break_level="NO_BREAK"/>
  <word text="22nd" break_level="SPACE_BREAK"/>
  <word text="March" break_level="SPACE_BREAK"/>
  <word text="." break_level="NO_BREAK"/>
  <word text="--" break_level="PARAGRAPH_BREAK"/>
  <word text="Dave" break_level="SENTENCE_BREAK"/>
  <word text="Raggett" break_level="SPACE_BREAK"/>
  <word text="tel" break_level="SPACE_BREAK"/>
  <word text=":" break_level="NO_BREAK"/>
  <word text="+1" break_level="SPACE_BREAK"/>
  <word text="(" break_level="SPACE_BREAK"/>
  <word text="617" break_level="NO_BREAK"/>
  <word text=")" break_level="NO_BREAK"/>
  <word text="258" break_level="SPACE_BREAK"/>
  <word text="5741" break_level="SPACE_BREAK"/>
  <word text="fax" break_level="SPACE_BREAK"/>
  <word text=":" break_level="NO_BREAK"/>
  <word text="+1" break_level="SPACE_BREAK"/>
  <word text="(" break_level="SPACE_BREAK"/>
  <word text="617" break_level="NO_BREAK"/>
  <word text=")" break_level="NO_BREAK"/>
  <word text="258" break_level="SPACE_BREAK"/>
  <word text="5999" break_level="SPACE_BREAK"/>
  <word text="World" break_level="LINE_BREAK"/>
  <word text="Wide" lemma="wide" pos="ADJ" sense="/dictionary/sense/en_us_NOAD3e_2012/m_en_us1306319.005" break_level="SPACE_BREAK"/>
  <word text="Web" break_level="SPACE_BREAK"/>
  <word text="Consortium" break_level="SPACE_BREAK"/>
  <word text="," break_level="NO_BREAK"/>
  <word text="545" break_level="SPACE_BREAK"/>
  <word text="Technology" break_level="SPACE_BREAK"/>
  <word text="Square" break_level="SPACE_BREAK"/>
  <word text="," break_level="NO_BREAK"/>
  <word text="Cambridge" break_level="SPACE_BREAK"/>
  <word text="," break_level="NO_BREAK"/>
  <word text="MA" break_level="SPACE_BREAK"/>
  <word text="02139" break_level="SPACE_BREAK"/>
  <word text="url" break_level="LINE_BREAK"/>
  <word text="=" break_level="SPACE_BREAK"/>
  <word text="http://www.w3.org/People/Raggett" break_level="SPACE_BREAK"/>
</SimpleWsdDoc>
